PyFileArranger/__init__.py
PyFileArranger-1.4.dist-info/LICENSE.txt
PyFileArranger-1.4.dist-info/METADATA
PyFileArranger-1.4.dist-info/WHEEL
PyFileArranger-1.4.dist-info/top_level.txt
PyFileArranger-1.4.dist-info/RECORD
