Metadata-Version: 2.1
Name: PyFileArranger
Version: 1.4
Summary: This is a File Arranger Module
Home-page: https://auxous.com
Author: Bikash Kumar Singh
Author-email: UNKNOWN
License: UNKNOWN
Platform: UNKNOWN
